README.md
magicdate.py
setup.cfg
setup.py
magicdate.egg-info/PKG-INFO
magicdate.egg-info/SOURCES.txt
magicdate.egg-info/dependency_links.txt
magicdate.egg-info/entry_points.txt
magicdate.egg-info/top_level.txt
magicdate.egg-info/zip-safe