Metadata-Version: 1.1
Name: magicdate
Version: 0.2
Summary: Convert fuzzy date to a datetime object.
Home-page: https://github.com/betodealmeida/magicdate
Author: Beto Dealmeida
Author-email: roberto@dealmeida.net
License: MIT
Download-URL: http://cheeseshop.python.org/packages/source/m/magicdate/magicdate-0.2.tar.gz
Keywords: datetime time
Platform: UNKNOWN
Classifier: Development Status :: 4 - Beta
Classifier: Environment :: Console
Classifier: Intended Audience :: Developers
Classifier: License :: OSI Approved :: MIT License
Classifier: Operating System :: OS Independent
Classifier: Programming Language :: Python
Classifier: Topic :: Software Development :: Libraries :: Python Modules
